{
"feed": 
    [
      {
        "header": "Unbeatable",
        "title": "Welcome to the hub", 
        "description": "We appreciate you for joining us here feel welcomed"
      },
      {
        "header": "Realistic",
        "title": "Welcome to the hub", 
        "description": "We appreciate you joining us here feel welcomed"
      },
      {
        "header": "Determined",
        "title": "Welcome to the hub", 
        "description": "We are determined appreciate you oining us here feel welcomed"
      },{
        "header": "Ready",
        "title": "Welcome to the hub", 
        "description": "We appreciate you oining us here feel welcomed"
      }
    ]
}
